chrome_devices_manager.py
devices.py
chrome_custom_devices-1.0.10.dist-info/licenses/LICENSE
chrome_custom_devices-1.0.10.dist-info/METADATA
chrome_custom_devices-1.0.10.dist-info/WHEEL
chrome_custom_devices-1.0.10.dist-info/entry_points.txt
chrome_custom_devices-1.0.10.dist-info/top_level.txt
chrome_custom_devices-1.0.10.dist-info/RECORD
