Metadata-Version: 2.4
Name: chrome-custom-devices
Version: 1.0.10
Summary: A comprehensive tool to add custom device presets to Chrome DevTools
Home-page: https://github.com/hatimmakki/chrome-custom-devices
Author: Hatim Makki
Author-email: hatim.makki@gmail.com
License: MIT
Project-URL: Bug Reports, https://github.com/hatimmakki/chrome-custom-devices/issues
Project-URL: Source, https://github.com/hatimmakki/chrome-custom-devices
Keywords: chrome devtools devices emulation responsive web development
Classifier: Development Status :: 5 - Production/Stable
Classifier: Intended Audience :: Developers
Classifier: Operating System :: OS Independent
Classifier: Programming Language :: Python :: 3
Classifier: Programming Language :: Python :: 3.6
Classifier: Programming Language :: Python :: 3.7
Classifier: Programming Language :: Python :: 3.8
Classifier: Programming Language :: Python :: 3.9
Classifier: Programming Language :: Python :: 3.10
Classifier: Programming Language :: Python :: 3.11
Classifier: Programming Language :: Python :: 3.12
Classifier: Topic :: Software Development
Classifier: Topic :: Internet :: WWW/HTTP :: Browsers
Classifier: Topic :: Utilities
Requires-Python: >=3.6
License-File: LICENSE
Dynamic: author
Dynamic: author-email
Dynamic: classifier
Dynamic: description
Dynamic: description-content-type
Dynamic: home-page
Dynamic: keywords
Dynamic: license
Dynamic: license-file
Dynamic: project-url
Dynamic: requires-python
Dynamic: summary
